ansidoc/__init__.py
ansidoc/__main__.py
ansidoc/__version__.py
ansidoc/ansidoclib.py
ansidoc/cli.py
ansidoc/helpers.py
ansidoc/templates/readme.j2
ansidoc/templates/readme_ansidoc_footer.j2
ansidoc/templates/readme_role_installation.j2
ansidoc/templates/readme_role_md_doc.j2
ansidoc/templates/readme_role_todo.j2
ansidoc/templates/readme_role_vars.j2
ansidoc-0.6.0.dist-info/DESCRIPTION.rst
ansidoc-0.6.0.dist-info/METADATA
ansidoc-0.6.0.dist-info/RECORD
ansidoc-0.6.0.dist-info/WHEEL
ansidoc-0.6.0.dist-info/entry_points.txt
ansidoc-0.6.0.dist-info/metadata.json
ansidoc-0.6.0.dist-info/top_level.txt
