Metadata-Version: 2.0
Name: ansidoc
Version: 0.6.0
Summary: Manage ansible role documentation
Home-page: https://github.com/archf/ansidoc
Author: Felix Archambault
Author-email: fel.archambault@gmail.com
License: MIT
Keywords: ansible,documentation generation
Platform: UNKNOWN
Classifier: Development Status :: 4 - Beta
Classifier: Intended Audience :: Developers
Classifier: Topic :: Software Development :: Build Tools
Classifier: Topic :: Software Development :: Documentation
Classifier: License :: OSI Approved :: MIT License
Classifier: Programming Language :: Python :: 3
Classifier: Programming Language :: Python :: 3.3
Classifier: Programming Language :: Python :: 3.4
Classifier: Programming Language :: Python :: 3.5
Requires-Dist: PyYaml
Requires-Dist: jinja2
Requires-Dist: tabulate
